Metadata-Version: 2.1
Name: ozonetel-ai
Version: 0.0.121
Summary: The Ozonetel AI Library is a powerful tool developed by Ozonetel Communications Pvt Ltd, designed to empower developers with state-of-the-art Artificial Intelligence capabilities. This library provides seamless integration of advanced AI models into your projects, allowing you to leverage the latest in AI technology to enhance your applications.
Home-page: 
Author: Biswajit Satapathy
Author-email: biswajit@ozonetel.com
License: MIT License
Keywords: Machine Learning,Artificial Intellegence,Neural Network,Indexing,Searching
Classifier: Programming Language :: Python :: 3.8
Classifier: Programming Language :: Python :: 3.9
Classifier: Programming Language :: Python :: 3.10
License-File: LICENSE
